MANIFEST.in
README.rst
setup.py
md2ebook/__init__.py
md2ebook/checkers.py
md2ebook/commander.py
md2ebook/exceptions.py
md2ebook/generators.py
md2ebook/md2ebook.py
md2ebook/ui.py
md2ebook.egg-info/PKG-INFO
md2ebook.egg-info/SOURCES.txt
md2ebook.egg-info/dependency_links.txt
md2ebook.egg-info/entry_points.txt
md2ebook.egg-info/not-zip-safe
md2ebook.egg-info/requires.txt
md2ebook.egg-info/top_level.txt