Metadata-Version: 1.0
Name: md2ebook
Version: 0.1.1
Summary: Build e-books (EPUB or PDF) out of markdown files
Home-page: https://github.com/brunobord/md2ebook/
Author: Bruno Bord
Author-email: bruno@jehaisleprintemps.net
License: MIT
Platform: UNKNOWN
Classifier: Development Status :: 4 - Beta
Classifier: Natural Language :: English
Classifier: License :: OSI Approved :: MIT License
Classifier: Operating System :: OS Independent
Classifier: Programming Language :: Python
Classifier: Programming Language :: Python :: 2
Classifier: Topic :: Text Processing
Classifier: Topic :: Text Processing :: Markup
